<meta>
	<info author="XRAY" version="0.1" name="Protect" description="by XRAY" type="script" />
	<script src="pedint_client.lua" type="client" />
	
	<file src="sounds/script/soldier_greeting_1.ogg" />
	<file src="sounds/script/soldier_greeting_2.ogg" />
	<file src="sounds/script/soldier_greeting_3.ogg" />
	<file src="sounds/script/soldier_greeting_4.ogg" />
	<file src="sounds/script/soldier_idle_1.ogg" />
	<file src="sounds/script/soldier_idle_2.ogg" />
	<file src="sounds/script/soldier_leave_1.ogg" />
	<file src="sounds/script/soldier_leave_2.ogg" />
	<file src="sounds/script/soldier_leave_3.ogg" />
	<file src="sounds/script/soldier_leave_4.ogg" />
	
	<file src="models/leatherjacket.txd" />
	<file src="models/leatherjacket.dff" />
	<file src="models/novichek.dff" />
	<file src="models/voenn.txd" />
	<file src="models/bandos.txd" />
	<file src="models/voenn.dff" />
	<file src="models/bandos.dff" />
	<file src="models/odinochka.txd" />
	<file src="models/odinochka.dff" />
	<file src="models/merc.txd" />
	<file src="models/merc.dff" />
	<file src="models/freedom.txd" />
	<file src="models/duty.txd" />
	<file src="models/armouredsuit.dff" />
	<file src="models/bandit.txd" />
	<file src="models/bandit.dff" />
	<file src="models/clearskyhood.txd" />
	<file src="models/clearskyhood.dff" />
	<file src="models/army.txd" />
	<file src="models/army.dff" />
	<file src="models/opitniy.txd" />
	<file src="models/opitniy.dff" />
	<file src="models/opitniy_bandos.txd" />
	<file src="models/opitniy_bandos.dff" />
	<file src="models/opitniy_bandos2.txd" />
	<file src="models/opitniy_bandos2.dff" />
	<file src="models/male01.txd" />
	<file src="models/male01.dff" />

	<file src="models/army/army.dff" />
	<file src="models/army/army.txd" />
	<file src="models/duty/bmycr.dff" />
	<file src="models/duty/bmycr.txd" />
	<file src="models/duty/dnb1.dff" />
	<file src="models/duty/dnb1.txd" />
	<file src="models/duty/dnb2.dff" />
	<file src="models/duty/dnb2.txd" />
	<file src="models/duty/dnb3.dff" />
	<file src="models/duty/dnb3.txd" />
	<file src="models/duty/fam1.dff" />
	<file src="models/duty/fam1.txd" />
	<file src="models/duty/fam2.dff" />
	<file src="models/duty/fam2.txd" />
	<file src="models/duty/fam3.dff" />
	<file src="models/duty/fam3.txd" />
	<file src="models/duty/vla1.dff" />
	<file src="models/duty/vla1.txd" />
	<file src="models/duty/vla2.dff" />
	<file src="models/duty/vla2.txd" />
	<file src="models/duty/vla3.dff" />
	<file src="models/duty/vla3.txd" />
	<file src="models/freedom/bmori.dff" />
	<file src="models/freedom/bmori.txd" />
	<file src="models/freedom/bmost.dff" />
	<file src="models/freedom/bmost.txd" />
	<file src="models/freedom/bmycr.dff" />
	<file src="models/freedom/bmycr.txd" />
	<file src="models/freedom/bmyri.dff" />
	<file src="models/freedom/bmyri.txd" />
	<file src="models/freedom/mafboss.dff" />
	<file src="models/freedom/mafboss.txd" />
	<file src="models/freedom/maffa.dff" />
	<file src="models/freedom/maffa.txd" />
	<file src="models/freedom/maffb.dff" />
	<file src="models/freedom/maffb.txd" />
	<file src="models/freedom/swmotr1.dff" />
	<file src="models/freedom/swmotr1.txd" />
	<file src="models/freedom/triada.dff" />
	<file src="models/freedom/triada.txd" />
	<file src="models/freedom/triadb.dff" />
	<file src="models/freedom/triadb.txd" />
	<file src="models/freedom/triboss.dff" />
	<file src="models/freedom/triboss.txd" />
	<file src="models/freedom/vmaff1.dff" />
	<file src="models/freedom/vmaff1.txd" />
	<file src="models/freedom/vmaff2.dff" />
	<file src="models/freedom/vmaff2.txd" />
	<file src="models/freedom/vmaff3.dff" />
	<file src="models/freedom/vmaff3.txd" />
	<file src="models/freedom/vmaff4.dff" />
	<file src="models/freedom/vmaff4.txd" />
	<file src="models/scientist/bikerb.dff" />
	<file src="models/scientist/bikerb.txd" />
	<file src="models/scientist/bmori.dff" />
	<file src="models/scientist/bmori.txd" />
	<file src="models/scientist/bmost.dff" />
	<file src="models/scientist/bmost.txd" />
	<file src="models/scientist/bmyap.dff" />
	<file src="models/scientist/bmyap.txd" />
	<file src="models/scientist/bmybar.dff" />
	<file src="models/scientist/bmybar.txd" />
	<file src="models/scientist/bmycr.dff" />
	<file src="models/scientist/bmycr.txd" />
	<file src="models/scientist/bmyri.dff" />
	<file src="models/scientist/bmyri.txd" />
	<file src="models/scientist/bmyst.dff" />
	<file src="models/scientist/bmyst.txd" />
	<file src="models/scientist/bmytatt.dff" />
	<file src="models/scientist/bmytatt.txd" />
	<file src="models/scientist/sfr1.dff" />
	<file src="models/scientist/sfr1.txd" />
	<file src="models/scientist/sfr2.dff" />
	<file src="models/scientist/sfr2.txd" />
	<file src="models/scientist/sfr3.dff" />
	<file src="models/scientist/sfr3.txd" />
	<file src="models/scientist/shmycr.dff" />
	<file src="models/scientist/shmycr.txd" />
	<file src="models/scientist/wmybar.dff" />
	<file src="models/scientist/wmybar.txd" />

	<file src="anims/wounded.ifp" />
</meta>
